[{"name":" CRITICAL CARE MEDFLIGHT INC"},{" CRITICAL CARE MEDFLIGHT INC":""},{" Airline internet site":" Not available"},{" FAA Designator Code":" MFGA"},{" Certificate Number":" MFGA228B"},{" Years In Business":" 32"},{" Certificate Issue Date":" 07/03/1986"},{" FAA Office":" ATLANTA FLT STDS DIST OFFICE"},{" FAA Office Phone Number":" (404) 474-5100"},{" Airline Information":""},{" Airline Address":" 530 BRISCOE BLVD.\n LAWRENCEVILLE , GA 30045"},{" Operation Kind":" 1. ON-DEMAND AIRPLANE (PAX / CARGO)\n"},{" Operator is doing business as":" 1. CRITICAL CARE MEDFLIGHT \n 2. GEORGIA JET \n"}]