[{"name":" UPPER LIMIT FLIGHT SERVICES INC"},{" UPPER LIMIT FLIGHT SERVICES INC":""},{" Airline internet site":" Not available"},{" FAA Designator Code":" QOQA"},{" Certificate Number":" QOQA379L"},{" Years In Business":" 12"},{" Certificate Issue Date":" 07/27/2006"},{" FAA Office":" SALT LAKE CITY FLT STDS DIST OFFICE"},{" FAA Office Phone Number":" (801) 257-5020"},{" Airline Information":""},{" Airline Address":" 619 NORTH 2360 WEST\n SALT LAKE CITY , UT 84116"},{" Operation Kind":" 1. ON-DEMAND ROTOCRAFT (PAX / CARGO)\n"},{" Operator is doing business as":" 1. Yeti Aviation \n"}]