[{"name":" ACE PILOT TRAINING INC"},{" ACE PILOT TRAINING INC":""},{" Airline internet site":" Not available"},{" FAA Designator Code":" GU7A"},{" Certificate Number":" GU7A529W"},{" Years In Business":" 11"},{" Certificate Issue Date":" 01/18/2007"},{" FAA Office":" ALLENTOWN FLT STDS DIST OFFICE"},{" FAA Office Phone Number":" (610) 264-2888"},{" Airline Information":""},{" Airline Address":" 600 HAYDEN CIRCLE\n ALLENTOWN , PA 18109"},{" Operation Kind":" 1. ON-DEMAND AIRPLANE (PAX / CARGO)\n"},{" Operator is doing business as":" 1. AP AIR CHARTER \n"}]