[{"name":" AMERICAN AIR CHARTER INC"},{" AMERICAN AIR CHARTER INC":""},{" Airline internet site":" Not available"},{" FAA Designator Code":" UUKA"},{" Certificate Number":" UUKA937U"},{" Years In Business":" 25"},{" Certificate Issue Date":" 08/01/1993"},{" FAA Office":" ST LOUIS FLT STDS DIST OFFICE"},{" FAA Office Phone Number":" (314) 890-4800"},{" Airline Information":""},{" Airline Address":" 577 BELL AVENUE\n CHESTERFIELD , MO 63005"},{" Operation Kind":" 1. ON-DEMAND AIRPLANE (PAX / CARGO)\n"}]