[{"name":" NEW ENGLAND LIFE FLIGHT INC"},{" NEW ENGLAND LIFE FLIGHT INC":""},{" Airline internet site":" Not available"},{" FAA Designator Code":" 6BMA"},{" Certificate Number":" 6BMA610N"},{" Years In Business":" 1"},{" Certificate Issue Date":" 02/22/2017"},{" FAA Office":" BOSTON FLIGHT STDS DIST OFFICE"},{" FAA Office Phone Number":" (781) 238-7500"},{" Airline Information":""},{" Airline Address":" 1727 ROBINS STREET\n BEDFORD , MA 01730"},{" Operation Kind":" 1. ON-DEMAND ROTOCRAFT (PAX / CARGO)\n"},{" Operator is doing business as":" 1. BOSTON MEDFLIGHT \n"}]