[{"name":" AIR SANTA BARBARA INC"},{" AIR SANTA BARBARA INC":""},{" Airline internet site":" Not available"},{" FAA Designator Code":" I93A"},{" Certificate Number":" I93A388L"},{" Years In Business":" 11"},{" Certificate Issue Date":" 03/19/2007"},{" FAA Office":" LONG BEACH FLT STDS DIST OFFICE"},{" FAA Office Phone Number":" (562) 420-1755"},{" Airline Information":""},{" Airline Address":" 5001 BIRCH STREET\n SUITE 33\n NEWPORT BEACH , CA 92660"},{" Operation Kind":" 1. ON-DEMAND AIRPLANE (PAX / CARGO)\n"}]