[{"name":" AIR RESOURCES HELICOPTERS INC"},{" AIR RESOURCES HELICOPTERS INC":""},{" Airline internet site":" Not available"},{" FAA Designator Code":" WIPA"},{" Certificate Number":" WIPA601S"},{" Years In Business":" 26"},{" Certificate Issue Date":" 02/20/1992"},{" FAA Office":" RIVERSIDE FLT STDS DIST OFFICE"},{" FAA Office Phone Number":" (951) 276-6701"},{" Airline Information":""},{" Airline Address":" 37350 SKY CANYON DRIVE\n SUITE 220\n MURRIETA , CA 92563"},{" Operation Kind":" 1. ON-DEMAND ROTOCRAFT (PAX / CARGO)\n"},{" Operator is doing business as":" 1. HELI-RESOURCES, INC. \n"}]