[{"name":" TWC AVIATION INC"},{" TWC AVIATION INC":""},{" Airline internet site":" Not available"},{" FAA Designator Code":" BZUA"},{" Certificate Number":" BZUA138N"},{" Years In Business":" 37"},{" Certificate Issue Date":" 09/14/1981"},{" FAA Office":" SAN JOSE FLT STDS DIST OFFICE"},{" FAA Office Phone Number":" (408) 291-7681"},{" Airline Information":""},{" Airline Address":" 323 MARTIN AVENUE\n TWO CORPORATE DRIVE\n SHELTON, CT O6484\n SAN JOSE , CA 95050"},{" Operation Kind":" 1. ON-DEMAND AIRPLANE (PAX / CARGO)\n"},{" Operator is doing business as":" 1. Gama Aviation Signature \n 2. Gama Aviation, LLC \n 3. Landmark Aviation \n"}]