[{"name":" ENTERPRISE PRODUCTS COMPANY"},{" ENTERPRISE PRODUCTS COMPANY":""},{" Airline internet site":" Not available"},{" FAA Designator Code":" 9EPA"},{" Certificate Number":" 9EPA035N"},{" Years In Business":" 7"},{" Certificate Issue Date":" 12/12/2011"},{" FAA Office":" HOUSTON FLT STDS DIST OFFICE"},{" FAA Office Phone Number":" (281) 929-7000"},{" Airline Information":""},{" Airline Address":" 1100 LOUISIANA STREET\n STE: 5200\n HOUSTON , TX 77002-5287"},{" Operation Kind":" 1. ON-DEMAND AIRPLANE (PAX / CARGO)\n"}]