[{"name":" ADVANCED AIR INC"},{" ADVANCED AIR INC":""},{" Airline internet site":" Not available"},{" FAA Designator Code":" PHKA"},{" Certificate Number":" PHKA735S"},{" Years In Business":" 28"},{" Certificate Issue Date":" 07/16/1990"},{" FAA Office":" DES MOINES FLT STDS DIST OFFICE"},{" FAA Office Phone Number":" (515) 289-3840"},{" Airline Information":""},{" Airline Address":" 101 MCCANDLESS LANE, STE 1\n MUNICIPAL AIRPORT\n COUNCIL BLUFFS , IA 51503"},{" Operation Kind":" 1. ON-DEMAND AIRPLANE (PAX / CARGO)\n"}]