[{"name":" BROWARD COUNTY SHERIFFS OFFICE"},{" BROWARD COUNTY SHERIFFS OFFICE":""},{" Airline internet site":" Not available"},{" FAA Designator Code":" B1EA"},{" Certificate Number":" B1EA573J"},{" Years In Business":" 16"},{" Certificate Issue Date":" 02/12/2002"},{" FAA Office":" SOUTH FLORIDA FSDO"},{" FAA Office Phone Number":" (954) 641-6000"},{" Airline Information":""},{" Airline Address":" 5253 NW 20 TERRACE\n FT. LAUDERDALE , FL 33309"},{" Operation Kind":" 1. ON-DEMAND ROTOCRAFT (PAX / CARGO)\n"}]