[{"name":" GLOBAL X GROUP INC"},{" GLOBAL X GROUP INC":""},{" Airline internet site":" Not available"},{" FAA Designator Code":" 8GXA"},{" Certificate Number":" 8GXA022N"},{" Years In Business":" 7"},{" Certificate Issue Date":" 06/15/2011"},{" FAA Office":" SOUTH FLORIDA FSDO"},{" FAA Office Phone Number":" (954) 641-6000"},{" Airline Information":""},{" Airline Address":" 3353 NE 2ND DRIVE\n HOMESTEAD , FL 33033"},{" Operation Kind":" 1. ON-DEMAND ROTOCRAFT (PAX / CARGO)\n"},{" Operator is doing business as":" 1. SOUTHERN CARIBBEAN HELICOPTERS \n 2. VIRGIN ISLAND HELICOPTERS \n"}]