[{"name":" MALONE AIRCHARTER INC"},{" MALONE AIRCHARTER INC":""},{" Airline internet site":" Not available"},{" FAA Designator Code":" Q3SA"},{" Certificate Number":" Q3SA041K"},{" Years In Business":" 16"},{" Certificate Issue Date":" 12/31/2002"},{" FAA Office":" ORLANDO FLT STD DST OFFICE"},{" FAA Office Phone Number":" (407) 487-7000"},{" Airline Information":""},{" Airline Address":" CRAIG MUNICIPAL AIRPORT\n 855-21 ST. JOHNS BLUFF ROAD\n JACKSONVILLE , FL 32225"},{" Operation Kind":" 1. ON-DEMAND AIRPLANE (PAX / CARGO)\n"},{" Operator is doing business as":" 1. POINT TO POINT AIR \n"}]