[{"name":" SOUTH FLORIDA AVIATION GROUP"},{" SOUTH FLORIDA AVIATION GROUP":""},{" Airline internet site":" Not available"},{" FAA Designator Code":" 9S7A"},{" Certificate Number":" 9S7A699N"},{" Years In Business":" 2"},{" Certificate Issue Date":" 06/10/2016"},{" FAA Office":" SOUTH FLORIDA FSDO"},{" FAA Office Phone Number":" (954) 641-6000"},{" Airline Information":""},{" Airline Address":" 965 BAY DRIVE, SUITE 6\n MIAMI BEACH , FL 33141"},{" Operation Kind":" 1. ON-DEMAND AIRPLANE (PAX / CARGO)\n"},{" Operator is doing business as":" 1. Caribbean Airways \n"}]